checkov_custom_policies/__init__.py
checkov_custom_policies/_version.py
checkov_custom_policies/py.typed
checkov_custom_policies/settings.py
checkov_custom_policies/setup.py
checkov_custom_policies/conf/__init__.py
checkov_custom_policies/conf/oneCloudTagsCheck.py
checkov_custom_policies/conf/settings.py
tests/__init__.py
checkov_custom_policies-0.0.0.dev0.dist-info/LICENSE
checkov_custom_policies-0.0.0.dev0.dist-info/METADATA
checkov_custom_policies-0.0.0.dev0.dist-info/WHEEL
checkov_custom_policies-0.0.0.dev0.dist-info/top_level.txt
checkov_custom_policies-0.0.0.dev0.dist-info/RECORD
